psycopg2/__init__.py
psycopg2/_ipaddress.py
psycopg2/_json.py
psycopg2/_psycopg.cpython-39-aarch64-linux-gnu.so
psycopg2/_range.py
psycopg2/errorcodes.py
psycopg2/errors.py
psycopg2/extensions.py
psycopg2/extras.py
psycopg2/pool.py
psycopg2/sql.py
psycopg2/tz.py
fv_aws_psycopg2_arm64-2.9.9.dist-info/LICENSE
fv_aws_psycopg2_arm64-2.9.9.dist-info/METADATA
fv_aws_psycopg2_arm64-2.9.9.dist-info/WHEEL
fv_aws_psycopg2_arm64-2.9.9.dist-info/top_level.txt
fv_aws_psycopg2_arm64-2.9.9.dist-info/RECORD
