Metadata-Version: 2.1
Name: fv-aws-psycopg2-arm64
Version: 2.9.9
Summary: psycopg2 - Python-PostgreSQL Database Adapter
Home-page: https://psycopg.org/
Author: Federico Di Gregorio
Author-email: fog@initd.org
Maintainer: Daniele Varrazzo
Maintainer-email: daniele.varrazzo@gmail.com
License: LGPL with exceptions
Project-URL: Homepage, https://psycopg.org/
Project-URL: Documentation, https://www.psycopg.org/docs/
Project-URL: Code, https://github.com/psycopg/psycopg2
Project-URL: Issue Tracker, https://github.com/psycopg/psycopg2/issues
Project-URL: Download, https://pypi.org/project/psycopg2/
Platform: any
Classifier: Development Status :: 5 - Production/Stable
Classifier: Intended Audience :: Developers
Classifier: License :: OSI Approved :: GNU Library or Lesser General Public License (LGPL)
Classifier: Programming Language :: Python
Classifier: Programming Language :: Python :: 3
Classifier: Programming Language :: Python :: 3.7
Classifier: Programming Language :: Python :: 3.8
Classifier: Programming Language :: Python :: 3.9
Classifier: Programming Language :: Python :: 3.10
Classifier: Programming Language :: Python :: 3.11
Classifier: Programming Language :: Python :: 3.12
Classifier: Programming Language :: Python :: 3 :: Only
Classifier: Programming Language :: Python :: Implementation :: CPython
Classifier: Programming Language :: C
Classifier: Programming Language :: SQL
Classifier: Topic :: Database
Classifier: Topic :: Database :: Front-Ends
Classifier: Topic :: Software Development
Classifier: Topic :: Software Development :: Libraries :: Python Modules
Classifier: Operating System :: Microsoft :: Windows
Classifier: Operating System :: Unix
Requires-Python: >=3.7
